nbfilter/__init__.py
nbfilter/clean.py
nbfilter-1.1.0.dist-info/METADATA
nbfilter-1.1.0.dist-info/RECORD
nbfilter-1.1.0.dist-info/WHEEL
nbfilter-1.1.0.dist-info/top_level.txt
nbfilter-1.1.0.dist-info/zip-safe
