Metadata-Version: 2.1
Name: nbfilter
Version: 1.1.0
Summary: Filter .ipynb (nbformat) files to improve integration with version control systems (VCS)
Home-page: https://github.com/chbrown/nbfilter
Author: Christopher Brown
Author-email: io@henrian.com
License: MIT
Platform: UNKNOWN
Classifier: Development Status :: 4 - Beta
Classifier: Framework :: IPython
Classifier: Framework :: Jupyter
Classifier: License :: OSI Approved :: MIT License
Classifier: Operating System :: OS Independent
Classifier: Programming Language :: Python
Classifier: Topic :: Software Development :: Version Control
Classifier: Topic :: Software Development :: Version Control :: Git
Requires-Dist: nbformat (>=4)
